heygen_mcp/__init__.py
heygen_mcp/api_client.py
heygen_mcp/server.py
heygen_mcp-0.0.3.dist-info/METADATA
heygen_mcp-0.0.3.dist-info/WHEEL
heygen_mcp-0.0.3.dist-info/entry_points.txt
heygen_mcp-0.0.3.dist-info/top_level.txt
heygen_mcp-0.0.3.dist-info/RECORD
