Metadata-Version: 2.4
Name: heygen-mcp
Version: 0.0.3
Summary: HeyGen MCP Server for AI Video Creation
Author-email: Eddy Kim <eddy@heygen.com>
License: MIT
Project-URL: Homepage, https://github.com/heygen-com/heygen-mcp
Project-URL: Bug Tracker, https://github.com/heygen-com/heygen-mcp/issues
Keywords: heygen,mcp,claude,ai,video,avatar
Classifier: Development Status :: 3 - Alpha
Classifier: Intended Audience :: Developers
Classifier: License :: OSI Approved :: MIT License
Classifier: Programming Language :: Python :: 3
Classifier: Programming Language :: Python :: 3.12
Requires-Python: >=3.12
Requires-Dist: mcp[cli]>=1.6.0
Requires-Dist: pydantic>=2.0.0
Requires-Dist: httpx>=0.27.0
Requires-Dist: python-dotenv>=1.0.0
Provides-Extra: dev
Requires-Dist: pytest; extra == "dev"
Requires-Dist: pytest-asyncio; extra == "dev"
Requires-Dist: ruff; extra == "dev"
Requires-Dist: build; extra == "dev"
Requires-Dist: twine; extra == "dev"
